LICENSE
dynamodb_session_web/__init__.py
dynamodb_session_web/_session.py
dynamodb_session_web/exceptions.py
dynamodb_session_web/py.typed
dynamodb_session_web-0.2.9.dist-info/LICENSE
dynamodb_session_web-0.2.9.dist-info/WHEEL
dynamodb_session_web-0.2.9.dist-info/METADATA
dynamodb_session_web-0.2.9.dist-info/RECORD
