Metadata-Version: 2.1
Name: dynamodb-session-web
Version: 0.2.9
Summary: Contains the core API for a DynamoDB-backed session
Home-page: https://github.com/JCapriotti/dynamodb-session-web
License: MIT
Keywords: DynamoDB,Session,Web
Author: Jason Capriotti
Author-email: jason.capriotti@gmail.com
Requires-Python: >=3.7,<4.0
Classifier: License :: OSI Approved :: MIT License
Classifier: Programming Language :: Python :: 3
Classifier: Programming Language :: Python :: 3.7
Classifier: Programming Language :: Python :: 3.8
Classifier: Programming Language :: Python :: 3.9
Classifier: Programming Language :: Python :: 3.10
Requires-Dist: boto3 (>=1.21.21,<2.0.0)
Requires-Dist: itsdangerous (>=2.1.1,<3.0.0)
Project-URL: Repository, https://github.com/JCapriotti/dynamodb-session-web
